approxy/__init__.py
approxy/approxy.py
approxy/cluster.py
approxy/partition.py
approxy/utils.py
approxy-0.0.1a1.dist-info/LICENSE
approxy-0.0.1a1.dist-info/METADATA
approxy-0.0.1a1.dist-info/WHEEL
approxy-0.0.1a1.dist-info/top_level.txt
approxy-0.0.1a1.dist-info/RECORD
